smemhack_win10_pro/__init__.py
smemhack_win10_pro/main.py
smemhack_win10_pro-1.3.dist-info/LICENSE.txt
smemhack_win10_pro-1.3.dist-info/METADATA
smemhack_win10_pro-1.3.dist-info/WHEEL
smemhack_win10_pro-1.3.dist-info/top_level.txt
smemhack_win10_pro-1.3.dist-info/RECORD
