Metadata-Version: 2.1
Name: smemhack_win10_pro
Version: 1.3
Summary: A special version of smemhack just for win 10 pro user
Author: Dickily
Author-email: dickilyyiu@gmail.com
License: Proprietary
Classifier: License :: Other/Proprietary License
Classifier: Programming Language :: Python :: 3
Classifier: Programming Language :: Python :: 3.8
Classifier: Operating System :: OS Independent
Requires-Python: >=3.8.18
License-File: LICENSE.txt
Requires-Dist: Pillow>=8.0.0
Requires-Dist: pyautogui>=0.9.53
Requires-Dist: pyperclip>=1.8.2
Requires-Dist: numpy>=1.20.0
Requires-Dist: keyboard>=0.13.5
Requires-Dist: fuzzywuzzy>=0.18.0
Requires-Dist: python-Levenshtein>=0.12.2
